tabletexifier/Cell.py
tabletexifier/Table.py
tabletexifier/__init__.py
tabletexifier/exceptions.py
tabletexifier/table_styles.py
test/__init__.py
test/test_basic_functions.py
test/test_table_styles.py
tabletexifier-0.3.4.dist-info/METADATA
tabletexifier-0.3.4.dist-info/WHEEL
tabletexifier-0.3.4.dist-info/top_level.txt
tabletexifier-0.3.4.dist-info/RECORD
