Metadata-Version: 2.2
Name: tabletexifier
Version: 0.3.4
Summary: Add your description here
Home-page: 
Author: Kamuish
Author-email: andremiguel952@gmail.com
Requires-Python: >=3.6
Requires-Dist: pytest-assume>=2.4.3
Requires-Dist: twine>=6.0.1
Dynamic: author
Dynamic: author-email
Dynamic: requires-python
